AUTHORS
CHANGES
LICENSE
MANIFEST.in
README.rst
setup.py
cmsplugin_satchmo/__init__.py
cmsplugin_satchmo/admin.py
cmsplugin_satchmo/cms_plugins.py
cmsplugin_satchmo/models.py
cmsplugin_satchmo.egg-info/PKG-INFO
cmsplugin_satchmo.egg-info/SOURCES.txt
cmsplugin_satchmo.egg-info/dependency_links.txt
cmsplugin_satchmo.egg-info/not-zip-safe
cmsplugin_satchmo.egg-info/top_level.txt
cmsplugin_satchmo/locale/cs/LC_MESSAGES/django.mo
cmsplugin_satchmo/locale/cs/LC_MESSAGES/django.po
cmsplugin_satchmo/locale/en/LC_MESSAGES/django.mo
cmsplugin_satchmo/locale/en/LC_MESSAGES/django.po
cmsplugin_satchmo/migrations/0001_initial.py
cmsplugin_satchmo/migrations/0001_initial.pyc
cmsplugin_satchmo/migrations/0002_auto__add_satchmositesetting.py
cmsplugin_satchmo/migrations/0002_auto__add_satchmositesetting.pyc
cmsplugin_satchmo/migrations/0003_auto__del_field_satchmocategorieslistplugin_category_url_path__del_fie.py
cmsplugin_satchmo/migrations/0003_auto__del_field_satchmocategorieslistplugin_category_url_path__del_fie.pyc
cmsplugin_satchmo/migrations/0004_auto__add_field_satchmocategorieslistplugin_title__add_field_satchmopr.py
cmsplugin_satchmo/migrations/0004_auto__add_field_satchmocategorieslistplugin_title__add_field_satchmopr.pyc
cmsplugin_satchmo/migrations/__init__.py
cmsplugin_satchmo/migrations/__init__.pyc
cmsplugin_satchmo/templates/cmsplugin_satchmo/categories_listing.html
cmsplugin_satchmo/templates/cmsplugin_satchmo/category.html
cmsplugin_satchmo/templates/cmsplugin_satchmo/product.html
cmsplugin_satchmo/templates/cmsplugin_satchmo/products_listing.html