Metadata-Version: 1.0
Name: cmsplugin-satchmo
Version: 0.2.1
Summary: The Satchmo plugin for Django CMS
Home-page: https://bitbucket.org/tomaasch/cmsplugin_satchmo.git
Author: Tomáš Benda
Author-email: tomas@labs.cz
License: MIT
Platform: UNKNOWN
